Flask_RRBAC-0.3.0.dist-info/LICENSE.txt
Flask_RRBAC-0.3.0.dist-info/METADATA
Flask_RRBAC-0.3.0.dist-info/RECORD
Flask_RRBAC-0.3.0.dist-info/WHEEL
Flask_RRBAC-0.3.0.dist-info/top_level.txt
flask_rrbac/__init__.py
flask_rrbac/defaults.py
flask_rrbac/messages.py
flask_rrbac/models/__init__.py
flask_rrbac/models/acl_role_mixin.py
flask_rrbac/models/acl_role_route_map_mixin.py
flask_rrbac/models/acl_route_mixin.py
flask_rrbac/models/acl_user_mixin.py
flask_rrbac/models/acl_user_role_map_mixin.py
