Metadata-Version: 2.1
Name: Flask-RRBAC
Version: 0.3.0
Summary: Role Route Based Access Control support for Flask
Home-page: https://github.com/dhruvaggarwal043/flask-rrbac
Author: Dhruv Aggarwal
Author-email: dhruvaggarwal043@gmail.com
License: MIT
Project-URL: Source, https://github.com/dhruv-aggarwal/flask-rrbac
Project-URL: Documentation, https://github.com/dhruv-aggarwal/flask-rrbac/blob/master/README.md
Project-URL: Tracker, https://github.com/dhruv-aggarwal/flask-rrbac/issues
Keywords: flask access control acl rbac
Platform: any
Classifier: Framework :: Flask
Classifier: Environment :: Web Environment
Classifier: License :: OSI Approved :: MIT License
Classifier: Operating System :: OS Independent
Classifier: Programming Language :: Python :: 2
Classifier: Programming Language :: Python :: 2.6
Classifier: Programming Language :: Python :: 2.7
Classifier: Development Status :: 3 - Alpha
Classifier: Intended Audience :: Developers
Classifier: Topic :: Software Development :: Build Tools
Requires-Python: ~=2.6
Requires-Dist: Flask (>=0.10)
